ob_dj_feature_flags/apis/__init__.py
ob_dj_feature_flags/apis/flags/__init__.py
ob_dj_feature_flags/apis/flags/serializers.py
ob_dj_feature_flags/apis/flags/urls.py
ob_dj_feature_flags/apis/flags/views.py
ob_dj_feature_flags/apis/todos/__init__.py
ob_dj_feature_flags/apis/todos/serializers.py
ob_dj_feature_flags/apis/todos/urls.py
ob_dj_feature_flags/apis/todos/views.py
ob_dj_feature_flags/core/__init__.py
ob_dj_feature_flags/core/flags/__init__.py
ob_dj_feature_flags/core/flags/admin.py
ob_dj_feature_flags/core/flags/apps.py
ob_dj_feature_flags/core/flags/managers.py
ob_dj_feature_flags/core/flags/models.py
ob_dj_feature_flags/core/flags/receivers.py
ob_dj_feature_flags/core/flags/migrations/0001_initial.py
ob_dj_feature_flags/core/flags/migrations/0002_auto_20230503_2339.py
ob_dj_feature_flags/core/flags/migrations/__init__.py
ob_dj_feature_flags/core/todos/__init__.py
ob_dj_feature_flags/core/todos/apps.py
ob_dj_feature_flags/core/todos/models.py
ob_dj_feature_flags/core/todos/migrations/0001_initial.py
ob_dj_feature_flags/core/todos/migrations/__init__.py
ob_dj_feature_flags/utils/__init__.py
ob_dj_feature_flags/utils/decorators.py
ob_dj_feature_flags/utils/model.py
ob_dj_feature_flags-0.0.4.dist-info/LICENSE
ob_dj_feature_flags-0.0.4.dist-info/METADATA
ob_dj_feature_flags-0.0.4.dist-info/WHEEL
ob_dj_feature_flags-0.0.4.dist-info/top_level.txt
ob_dj_feature_flags-0.0.4.dist-info/RECORD
